u2_img/__init__.py
u2_img/comparison.py
u2_img/find_img.py
u2_img/imgUtil.py
u2_img-0.0.5.dist-info/METADATA
u2_img-0.0.5.dist-info/WHEEL
u2_img-0.0.5.dist-info/RECORD
